README.rst
setup.cfg
setup.py
hops/__init__.py
hops/constants.py
hops/credentials_provider.py
hops/dataset.py
hops/devices.py
hops/elasticsearch.py
hops/exceptions.py
hops/experiment.py
hops/featurestore.py
hops/hdfs.py
hops/hive.py
hops/jobs.py
hops/kafka.py
hops/model.py
hops/numpy_helper.py
hops/pandas_helper.py
hops/project.py
hops/secret.py
hops/service_discovery.py
hops/serving.py
hops/tensorboard.py
hops/tls.py
hops/user.py
hops/util.py
hops/version.py
hops/xattr.py
hops.egg-info/PKG-INFO
hops.egg-info/SOURCES.txt
hops.egg-info/dependency_links.txt
hops.egg-info/requires.txt
hops.egg-info/top_level.txt
hops/experiment_impl/__init__.py
hops/experiment_impl/launcher.py
hops/experiment_impl/distribute/__init__.py
hops/experiment_impl/distribute/mirrored.py
hops/experiment_impl/distribute/mirrored_reservation.py
hops/experiment_impl/distribute/mirrored_reservation_client.py
hops/experiment_impl/distribute/parameter_server.py
hops/experiment_impl/distribute/parameter_server_client.py
hops/experiment_impl/distribute/parameter_server_reservation.py
hops/experiment_impl/parallel/__init__.py
hops/experiment_impl/parallel/differential_evolution.py
hops/experiment_impl/parallel/grid_search.py
hops/experiment_impl/parallel/random_search.py
hops/experiment_impl/util/__init__.py
hops/experiment_impl/util/experiment_utils.py