Metadata-Version: 2.1
Name: hops
Version: 2.5.0.0
Summary: Client library for interacting with Hopsworks, a full-stack platform for scale-out data science.
Home-page: https://github.com/logicalclocks/hops-util-py
Author: Robin Andersson
Author-email: robin.eric.andersson@gmail.com
License: Apache License 2.0
Download-URL: http://snurran.sics.se/hops/hops-util-py/hops-2.5.0.0.tar.gz
Keywords: Hops,Hadoop,TensorFlow,Spark
Platform: UNKNOWN
Classifier: Development Status :: 5 - Production/Stable
Classifier: Topic :: Utilities
Classifier: License :: OSI Approved :: Apache Software License
Classifier: Programming Language :: Python :: 3
Provides-Extra: pydoop
Provides-Extra: tf
Provides-Extra: docs
Provides-Extra: test
Provides-Extra: spark
Provides-Extra: plotting
